online_deterministic_annealing/__init__.py
online_deterministic_annealing/oda.py
online_deterministic_annealing-1.0.2.dist-info/METADATA
online_deterministic_annealing-1.0.2.dist-info/WHEEL
online_deterministic_annealing-1.0.2.dist-info/RECORD
