Metadata-Version: 2.4
Name: online-deterministic-annealing
Version: 1.0.2
Summary: Online Deterministic Annealing Algorithm
Project-URL: Homepage, https://mavridischristos.github.io/
Project-URL: Repository, https://github.com/MavridisChristos/online-deterministic-annealing
Author-email: Christos Mavridis <mavridis@kth.se>
Maintainer-email: Christos Mavridis <mavridis@kth.se>
License-Expression: MIT
Keywords: annealing,classification,clustering,hybrid system identification,machine learning,optimization,regression,system identification
Classifier: Development Status :: 4 - Beta
Classifier: Intended Audience :: Developers
Classifier: Programming Language :: Python
Requires-Python: >=3.8
Requires-Dist: matplotlib>=3.10.3
Requires-Dist: numba>=0.61.2
Requires-Dist: numpy>=2.2.6
Requires-Dist: scipy>=1.16.2
Requires-Dist: shapely>=2.1.2
Provides-Extra: dev
Requires-Dist: ipykernel>=6.29.5; extra == 'dev'
